niclasProject/__init__.py
niclasProject/niclasProject.py
niclasProject-0.0.1.dist-info/LICENSE
niclasProject-0.0.1.dist-info/METADATA
niclasProject-0.0.1.dist-info/WHEEL
niclasProject-0.0.1.dist-info/top_level.txt
niclasProject-0.0.1.dist-info/RECORD
