Metadata-Version: 2.1
Name: niclasProject
Version: 0.0.1
Summary: A package to convert your Jupyter Notebook
Home-page: https://github.com/NiclasHjortkjaer/pyProject/
Author: Niclas Søgaard Hjortkjær
Author-email: hjortkjaer.niclas@gmail.com
License: UNKNOWN
Platform: UNKNOWN
Classifier: Programming Language :: Python :: 3.7
Classifier: License :: OSI Approved :: GNU General Public License v3 (GPLv3)
License-File: LICENSE
Requires-Dist: ipython (>=6)
Requires-Dist: nbformat (>=4)
Requires-Dist: nbconvert (>=5)
Requires-Dist: requests (>=2)
